mcp_my_apple_remembers/__init__.py
mcp_my_apple_remembers/server.py
mseep_mcp_my_apple_remembers-0.1.1.dist-info/METADATA
mseep_mcp_my_apple_remembers-0.1.1.dist-info/WHEEL
mseep_mcp_my_apple_remembers-0.1.1.dist-info/entry_points.txt
mseep_mcp_my_apple_remembers-0.1.1.dist-info/licenses/LICENSE
mseep_mcp_my_apple_remembers-0.1.1.dist-info/RECORD
