Metadata-Version: 2.4
Name: mseep-mcp_my_apple_remembers
Version: 0.1.1
Summary: A simple Apple Remembers MCP server
Author-email: mseep <support@skydeck.ai>
License-File: LICENSE
Requires-Python: >=3.10
Requires-Dist: mcp>=1.4.1
Requires-Dist: paramiko>=3.5.1
Requires-Dist: python-dotenv>=1.0.1
